odoo/addons/account_payment_show_invoice/README.rst
odoo/addons/account_payment_show_invoice/__manifest__.py
odoo/addons/account_payment_show_invoice/i18n/account_payment_show_invoice.pot
odoo/addons/account_payment_show_invoice/readme/CONTRIBUTORS.rst
odoo/addons/account_payment_show_invoice/readme/DESCRIPTION.rst
odoo/addons/account_payment_show_invoice/readme/USAGE.rst
odoo/addons/account_payment_show_invoice/static/description/icon.png
odoo/addons/account_payment_show_invoice/static/description/index.html
odoo/addons/account_payment_show_invoice/views/account_payment_view.xml
odoo13_addon_account_payment_show_invoice-13.0.1.0.2.dev6.dist-info/METADATA
odoo13_addon_account_payment_show_invoice-13.0.1.0.2.dev6.dist-info/WHEEL
odoo13_addon_account_payment_show_invoice-13.0.1.0.2.dev6.dist-info/top_level.txt
odoo13_addon_account_payment_show_invoice-13.0.1.0.2.dev6.dist-info/RECORD
