Metadata-Version: 2.1
Name: odoo13-addon-account-payment-show-invoice
Version: 13.0.1.0.2.dev6
Summary: Extends the tree view of payments to show the paid invoices related to the payments using the vendor reference by default
Home-page: https://github.com/OCA/account-payment
Author: Eficent, Odoo Community Association (OCA)
Author-email: support@odoo-community.org
License: AGPL-3
Platform: UNKNOWN
Classifier: Programming Language :: Python
Classifier: Framework :: Odoo
Classifier: Framework :: Odoo :: 13.0
Classifier: License :: OSI Approved :: GNU Affero General Public License v3
Requires-Python: >=3.5
Requires-Dist: odoo <13.1dev,>=13.0a
